subunit2sql/__init__.py
subunit2sql/exceptions.py
subunit2sql/read_subunit.py
subunit2sql/shell.py
subunit2sql/write_subunit.py
subunit2sql/analysis/__init__.py
subunit2sql/analysis/agg_count.py
subunit2sql/analysis/ci_time.py
subunit2sql/analysis/dailycount.py
subunit2sql/analysis/failures.py
subunit2sql/analysis/graph.py
subunit2sql/analysis/run_failure_rate.py
subunit2sql/analysis/run_time.py
subunit2sql/analysis/run_time_meta.py
subunit2sql/analysis/test_run_time.py
subunit2sql/analysis/utils.py
subunit2sql/db/__init__.py
subunit2sql/db/api.py
subunit2sql/db/models.py
subunit2sql/migrations/README
subunit2sql/migrations/__init__.py
subunit2sql/migrations/alembic.ini
subunit2sql/migrations/cli.py
subunit2sql/migrations/env.py
subunit2sql/migrations/script.py.mako
subunit2sql/migrations/versions/10a2b6d4b06e_add_even_more_indexes.py
subunit2sql/migrations/versions/13d819bbb0ff_create_missing_indexes.py
subunit2sql/migrations/versions/163fd5aa1380_create_avg_runtime_column_in_test_table.py
subunit2sql/migrations/versions/1679b5bc102c_add_subsecond_columns_to_test_runs_table.mysql_upgrade.sql
subunit2sql/migrations/versions/1679b5bc102c_add_subsecond_columns_to_test_runs_table.py
subunit2sql/migrations/versions/1f92cfe8a6d3_create_runs_table.py
subunit2sql/migrations/versions/1ff737bef438_add_indexes_on_common_search_fields.py
subunit2sql/migrations/versions/2822a408bdd0_uuid_to_integer_ids.py
subunit2sql/migrations/versions/28ac1ba9c3db_add_run_order_column.py
subunit2sql/migrations/versions/2fb76f1a1393_rename_test_id_column_in_test_metadata_.py
subunit2sql/migrations/versions/35cd45895e56_add_missing_fk_indexes.py
subunit2sql/migrations/versions/3db7b49816d5_create_test_runs_table.py
subunit2sql/migrations/versions/487f279b8c78_add_attachments_table.py
subunit2sql/migrations/versions/4ca26dac400e_create_metadata_tables.py
subunit2sql/migrations/versions/5332fe255095_populate_run_time_for_existing_tests.py
subunit2sql-1.10.0.dist-info/METADATA
subunit2sql-1.10.0.dist-info/RECORD
subunit2sql-1.10.0.dist-info/WHEEL
subunit2sql-1.10.0.dist-info/entry_points.txt
subunit2sql-1.10.0.dist-info/pbr.json
subunit2sql-1.10.0.dist-info/top_level.txt
