Metadata-Version: 2.1
Name: subunit2sql
Version: 1.10.0
Summary: Command to Read a subunit file or stream and put the data in a SQL DB
Home-page: UNKNOWN
Author: Matthew Treinish
Author-email: mtreinish@kortar.org
License: Apache License, Version 2.0
Platform: UNKNOWN
Classifier: Intended Audience :: Developers
Classifier: License :: OSI Approved :: Apache Software License
Classifier: Operating System :: OS Independent
Classifier: Programming Language :: Python
Classifier: Programming Language :: Python :: 2
Classifier: Programming Language :: Python :: 3
Provides-Extra: graph
Provides-Extra: test
Requires-Dist: pbr (!=2.1.0,>=2.0.0)
Requires-Dist: alembic (>=0.8.10)
Requires-Dist: oslo.config (>=4.0.0)
Requires-Dist: oslo.db (>=4.24.0)
Requires-Dist: python-subunit (>=0.0.18)
Requires-Dist: six (>=1.9.0)
Requires-Dist: SQLAlchemy (!=1.1.5,!=1.1.6,!=1.1.7,!=1.1.8,>=1.0.10)
Requires-Dist: stevedore (>=1.20.0)
Requires-Dist: python-dateutil (>=2.4.2)
Provides-Extra: graph
Requires-Dist: pandas (>=0.20.1); extra == 'graph'
Requires-Dist: matplotlib (>=2.0.2); extra == 'graph'
Provides-Extra: test
Requires-Dist: hacking (!=0.13.0,<0.14,>=0.12.0); extra == 'test'
Requires-Dist: coverage (>=3.6); extra == 'test'
Requires-Dist: fixtures (>=0.3.14); extra == 'test'
Requires-Dist: mock (>=1.0); extra == 'test'
Requires-Dist: sphinx (>=1.6.2); extra == 'test'
Requires-Dist: testscenarios (>=0.4); extra == 'test'
Requires-Dist: stestr (>=1.0.0); extra == 'test'
Requires-Dist: testtools (>=0.9.34); extra == 'test'
Requires-Dist: PyMySql; extra == 'test'
Requires-Dist: psycopg2; extra == 'test'
Requires-Dist: oslo.concurrency (>=3.5.0); extra == 'test'
Requires-Dist: reno (>=0.1.1); extra == 'test'
Requires-Dist: openstackdocstheme (>=1.11.0); extra == 'test'
Requires-Dist: testresources (>=0.2.4); extra == 'test'
Requires-Dist: testscenarios (>=0.4); extra == 'test'
